AUTHORS.rst
CONTRIBUTING.rst
HISTORY.rst
LICENSE.rst
MANIFEST.in
README.rst
VERSION
setup.cfg
setup.py
test-requirements.txt
docs/authors.rst
docs/conf.py
docs/contributing.rst
docs/history.rst
docs/index.rst
docs/installation.rst
docs/readme.rst
docs/usage.rst
pyWOA/__init__.py
pyWOA/utils.py
pyWOA/woa.py
pyWOA.egg-info/PKG-INFO
pyWOA.egg-info/SOURCES.txt
pyWOA.egg-info/dependency_links.txt
pyWOA.egg-info/not-zip-safe
pyWOA.egg-info/requires.txt
pyWOA.egg-info/top_level.txt
tests/test_WOA_from_nc.py