Metadata-Version: 1.1
Name: pyWOA
Version: 0.1.2
Summary: Package to subsample World Ocean Atlas climatology.
Home-page: https://github.com/castelao/pyWOA
Author: Guilherme Castelao
Author-email: guilherme@castelao.net
License: 3-clause BSD
Keywords: WOA World Ocean Atlas climatology oceanographic data oceanography temperature salinity
Platform: UNKNOWN
Classifier: Development Status :: 3 - Alpha
Classifier: Intended Audience :: Science/Research
Classifier: License :: OSI Approved :: BSD License
Classifier: Programming Language :: Python :: 2
Classifier: Programming Language :: Python :: 2.7
Classifier: Programming Language :: Python :: 3
Classifier: Programming Language :: Python :: 3.5
Classifier: Topic :: Scientific/Engineering
